{
  "repos": {
    "vedavaapi": {
        "db_type": "mongo",
        "mongo_host": "mongodb://127.0.0.1:27017",
        "db_prefix": "vedavaapi",
        "file_store_base_path": "vedavaapi"
    },
    "vedavaapi_test": {
        "db_type": "mongo",
        "mongo_host": "mongodb://127.0.0.1:27017",
        "db_prefix": "vedavaapi_test",
        "file_store_base_path": "vedavaapi_test"
    },
    "raifox_team": {
        "db_type": "mongo",
        "mongo_host": "mongodb://127.0.0.1:27017",
        "db_prefix": "raifox_team",
        "file_store_base_path": "raifox_team"
    },
    "demo": {
        "db_type": "mongo",
        "mongo_host": "mongodb://127.0.0.1:27017",
        "db_prefix": "demo",
        "file_store_base_path": "demo"
    }
  }
}
